{"assets":{"61779DC6DF9BEC3030218BE8972F1D00":{"type":"texture","index":0,"assetRequest":{"type":"slide","state":"contents","slide":"none"},"url":{"native":"assets\/80CC86AA-A338-4B62-A6CF-CC42F5DAFBC2.pdf"},"width":1024,"height":768},"4A4088A519EFA71653F10741CDBE7654":{"type":"texture","index":1,"assetRequest":{"type":"slide","state":"contents","slide":"none"},"url":{"native":"assets\/80CC86AA-A338-4B62-A6CF-CC42F5DAFBC2.pdf"},"width":1024,"height":768}},"events":[{"effects":[{"beginTime":0,"baseLayer":{"animations":[],"initialState":{"affineTransform":[1,0,0,1,0,0],"masksToBounds":false,"rotation":0,"scale":1,"position":{"pointX":512,"pointY":384},"width":1024,"sublayerTransform":[1,0,0,0,0,1,0,0,0,0,1,0,0,0,0,1],"contentsRect":{"y":0,"x":0,"width":1,"height":1},"opacity":1,"edgeAntialiasingMask":251658240,"height":768,"hidden":false,"anchorPoint":{"pointX":0.5,"pointY":0.5}},"objectID":"0","layers":[{"animations":[],"initialState":{"affineTransform":[1,0,0,1,0,0],"masksToBounds":false,"rotation":0,"scale":1,"position":{"pointX":512,"pointY":384},"width":1024,"sublayerTransform":[1,0,0,0,0,1,0,0,0,0,1,-0.00049229876906403734,0,0,0,1],"contentsRect":{"y":0,"x":0,"width":1,"height":1},"opacity":1,"edgeAntialiasingMask":251658240,"height":768,"hidden":false,"anchorPoint":{"pointX":0.5,"pointY":0.5}},"layers":[{"animations":[],"layers":[],"texturedRectangle":{"isBackgroundTexture":false,"singleTextureOpacity":1,"textureType":0,"textBaseline":0,"textXHeight":0,"isVerticalText":false},"initialState":{"affineTransform":[1,0,0,1,0,0],"masksToBounds":false,"rotation":0,"scale":1,"position":{"pointX":512,"pointY":384},"width":1024,"sublayerTransform":[1,0,0,0,0,1,0,0,0,0,1,0,0,0,0,1],"contentsRect":{"y":0,"x":0,"width":1,"height":1},"opacity":1,"edgeAntialiasingMask":0,"height":768,"hidden":false,"anchorPoint":{"pointX":0.5,"pointY":0.5}},"texture":"4A4088A519EFA71653F10741CDBE7654"},{"animations":[{"timeOffset":0,"from":{"scalar":false},"beginTime":0,"repeatCount":0,"fillMode":"both","property":"hidden","autoreverses":false,"duration":0.01,"to":{"scalar":true}}],"layers":[],"texturedRectangle":{"isBackgroundTexture":false,"singleTextureOpacity":1,"textureType":0,"textBaseline":0,"textXHeight":0,"isVerticalText":false},"initialState":{"affineTransform":[1,0,0,1,0,0],"masksToBounds":false,"rotation":0,"scale":1,"position":{"pointX":512,"pointY":384},"width":1024,"sublayerTransform":[1,0,0,0,0,1,0,0,0,0,1,0,0,0,0,1],"contentsRect":{"y":0,"x":0,"width":1,"height":1},"opacity":1,"edgeAntialiasingMask":0,"height":768,"hidden":false,"anchorPoint":{"pointX":0.5,"pointY":0.5}},"texture":"61779DC6DF9BEC3030218BE8972F1D00"}]}]},"effects":[],"duration":0.01,"type":"transition","attributes":{"direction":0},"name":"none","objectID":"0"}],"automaticPlay":false,"hyperlinks":[{"url":"http:\/\/www.w3.org\/TR\/DOM-Level-3-Core\/core.html#ID-637646024","targetRectangle":{"y":540.24477492336996,"x":414.32000009012006,"width":25.04000000000002,"height":17.552001953125}}],"accessibility":[{"text":"При чтении HTML браузер генерирует DOM-модель. При этом большинство стандартных HTML-атрибутов становятся свойствами соответствующих объектов.","targetRectangle":{"y":96.00478468899496,"x":104.00000009012001,"width":814,"height":35.552001953125}},{"text":"Свои DOM-свойства","targetRectangle":{"y":150.00478468899496,"x":104.00000009012001,"width":163.85599999999999,"height":18.535888671875}},{"text":"Ранее мы видели некоторые встроенные свойства DOM-узлов. Но, технически, никто нас ими не ограничивает.","targetRectangle":{"y":169.00478468899496,"x":104.00000009012001,"width":740.4000000000002,"height":35.552001953125}},{"text":"Узел DOM – это объект, поэтому, как и любой объект в JavaScript, он может содержать пользовательские свойства и методы.","targetRectangle":{"y":205.00478468899496,"x":104.00000009012001,"width":707.7120000000001,"height":37.535888671875}},{"text":"DOM-свойства:","targetRectangle":{"y":262.00478468899496,"x":104.00000009012001,"width":116.73599999999999,"height":17.552001953125}},{"text":"\\tМогут иметь любое значение.","targetRectangle":{"y":280.00478468899496,"x":140.00000009012001,"width":261.26400000000007,"height":17.552001953125}},{"text":"\\tНазвания свойств чувствительны к регистру.","targetRectangle":{"y":298.00478468899496,"x":140.00000009012001,"width":377.24799999999982,"height":17.552001953125}},{"text":"\\tРаботают за счёт того, что DOM-узлы являются объектами JavaScript.","targetRectangle":{"y":316.00478468899496,"x":140.00000009012001,"width":569.67999999999995,"height":17.552001953125}},{"text":"Атрибуты","targetRectangle":{"y":352.00478468899496,"x":104.00000009012001,"width":76.864000000000004,"height":18.535888671875}},{"text":"Элементам DOM, с другой стороны, соответствуют HTML-теги, у которых есть текстовые атрибуты.","targetRectangle":{"y":371.00478468899496,"x":104.00000009012001,"width":759.51999999999987,"height":17.552001953125}},{"text":"Доступ к атрибутам осуществляется при помощи стандартных методов:","targetRectangle":{"y":407.00478468899496,"x":104.00000009012001,"width":547.77599999999984,"height":17.552001953125}},{"text":"\\telem.hasAttribute(name) – проверяет наличие атрибута","targetRectangle":{"y":425.00478468899496,"x":140.00000009012001,"width":491.45868749999977,"height":19}},{"text":"\\telem.getAttribute(name) – получает значение атрибута","targetRectangle":{"y":444.45278273586996,"x":140.00000009012001,"width":488.2266874999998,"height":19}},{"text":"\\telem.setAttribute(name, value) – устанавливает атрибут","targetRectangle":{"y":463.90078078274496,"x":140.00000009012001,"width":515.52837499999976,"height":19}},{"text":"\\telem.removeAttribute(name) – удаляет атрибут","targetRectangle":{"y":483.34877882961996,"x":140.00000009012001,"width":426.51712499999985,"height":19}},{"text":"Также все атрибуты элемента можно получить с помощью свойства elem.attributes, которое содержит псевдо-массив объектов типа Attr.","targetRectangle":{"y":520.79677687649496,"x":104.00000009012001,"width":742.58818750000023,"height":37}},{"text":"В отличие от свойств, атрибуты:","targetRectangle":{"y":558.24477492336996,"x":104.00000009012001,"width":245.47200000000004,"height":17.552001953125}},{"text":"\\tВсегда являются строками.","targetRectangle":{"y":576.24477492336996,"x":140.00000009012001,"width":245.79200000000003,"height":17.552001953125}},{"text":"\\tИх имя нечувствительно к регистру (ведь это HTML)","targetRectangle":{"y":594.24477492336996,"x":140.00000009012001,"width":430.22399999999993,"height":17.552001953125}},{"text":"\\tВидны в innerHTML (за исключением старых IE)","targetRectangle":{"y":612.24477492336996,"x":140.00000009012001,"width":402.37531249999995,"height":19}},{"text":"Исходное значение value","targetRectangle":{"y":649.69277297024496,"x":104.00000009012001,"width":201.08799999999997,"height":18.535888671875}},{"text":"Изменение некоторых свойств обновляет атрибут. Но это скорее исключение, чем правило.","targetRectangle":{"y":668.69277297024496,"x":104.00000009012001,"width":700.70400000000006,"height":17.552001953125}},{"text":"Чаще синхронизация – односторонняя: свойство зависит от атрибута, но не наоборот.","targetRectangle":{"y":686.69277297024496,"x":104.00000009012001,"width":694.11199999999997,"height":18.535888671875}},{"text":"9. Атрибуты и DOM-свойства","targetRectangle":{"y":39.234448209333721,"x":279.96800001597069,"width":464.06399999999985,"height":38.07177734375}}],"baseLayer":{"animations":[],"initialState":{"affineTransform":[1,0,0,1,0,0],"masksToBounds":false,"rotation":0,"scale":1,"position":{"pointX":512,"pointY":384},"width":1024,"sublayerTransform":[1,0,0,0,0,1,0,0,0,0,1,0,0,0,0,1],"contentsRect":{"y":0,"x":0,"width":1,"height":1},"opacity":1,"edgeAntialiasingMask":251658240,"height":768,"hidden":false,"anchorPoint":{"pointX":0.5,"pointY":0.5}},"objectID":"0","layers":[{"animations":[],"initialState":{"affineTransform":[1,0,0,1,0,0],"masksToBounds":false,"rotation":0,"scale":1,"position":{"pointX":512,"pointY":384},"width":1024,"sublayerTransform":[1,0,0,0,0,1,0,0,0,0,1,-0.00049229876906403734,0,0,0,1],"contentsRect":{"y":0,"x":0,"width":1,"height":1},"opacity":1,"edgeAntialiasingMask":251658240,"height":768,"hidden":false,"anchorPoint":{"pointX":0.5,"pointY":0.5}},"layers":[{"animations":[],"layers":[],"texturedRectangle":{"isBackgroundTexture":false,"singleTextureOpacity":1,"textureType":0,"textBaseline":0,"textXHeight":0,"isVerticalText":false},"initialState":{"affineTransform":[1,0,0,1,0,0],"masksToBounds":false,"rotation":0,"scale":1,"position":{"pointX":512,"pointY":384},"width":1024,"sublayerTransform":[1,0,0,0,0,1,0,0,0,0,1,0,0,0,0,1],"contentsRect":{"y":0,"x":0,"width":1,"height":1},"opacity":1,"edgeAntialiasingMask":0,"height":768,"hidden":false,"anchorPoint":{"pointX":0.5,"pointY":0.5}},"texture":"61779DC6DF9BEC3030218BE8972F1D00"}]}]}}]}